odoo/addons/crm_project_create/README.rst
odoo/addons/crm_project_create/__init__.py
odoo/addons/crm_project_create/__manifest__.py
odoo/addons/crm_project_create/i18n/crm_project_create.pot
odoo/addons/crm_project_create/i18n/es.po
odoo/addons/crm_project_create/i18n/it.po
odoo/addons/crm_project_create/models/__init__.py
odoo/addons/crm_project_create/models/crm_lead.py
odoo/addons/crm_project_create/readme/CONTEXT.md
odoo/addons/crm_project_create/readme/CONTRIBUTORS.md
odoo/addons/crm_project_create/readme/DESCRIPTION.md
odoo/addons/crm_project_create/readme/USAGE.md
odoo/addons/crm_project_create/security/ir.model.access.csv
odoo/addons/crm_project_create/static/description/icon.png
odoo/addons/crm_project_create/static/description/index.html
odoo/addons/crm_project_create/tests/__init__.py
odoo/addons/crm_project_create/tests/test_crm_create_project.py
odoo/addons/crm_project_create/views/crm_lead.xml
odoo/addons/crm_project_create/wizards/__init__.py
odoo/addons/crm_project_create/wizards/crm_create_project.py
odoo/addons/crm_project_create/wizards/crm_create_project.xml
odoo_addon_crm_project_create-18.0.1.0.1.dist-info/METADATA
odoo_addon_crm_project_create-18.0.1.0.1.dist-info/WHEEL
odoo_addon_crm_project_create-18.0.1.0.1.dist-info/top_level.txt
odoo_addon_crm_project_create-18.0.1.0.1.dist-info/RECORD
