Metadata-Version: 2.1
Name: odoo-addon-crm_project_create
Version: 18.0.1.0.1
Requires-Python: >=3.10
Requires-Dist: odoo-addon-mail_message_destiny_link_template==18.0.*
Requires-Dist: odoo==18.0.*
Summary: Allow create projects from lead/opportunity
Home-page: https://github.com/OCA/crm
License: LGPL-3
Author: Moduon, Odoo Community Association (OCA)
Author-email: support@odoo-community.org
Classifier: Programming Language :: Python
Classifier: Framework :: Odoo
Classifier: Framework :: Odoo :: 18.0
Classifier: License :: OSI Approved :: GNU Lesser General Public License v3 (LGPLv3)
